{
    "openapi": "3.0.0",
    "info": {
        "title": "Response API",
        "version": "1.0.0"
    },
    "paths": { },
    "components": {
        "schemas": { },
        "responses": {
           "tokenResponse": {
                "description": "Get an oAuth2 Acces token",
                "content": {
                    "application/json": {
                        "schema": {
                            "properties": {
                                "access_token": {
                                    "type": "string",
                                    "example": "ABCDEFGHIJKLMNOPQRSTUVWXYZabcdefghijklmnopqrstuvwxyz0123456789"
                                },
                                "expires_at": {
                                    "type": "string",
                                    "format": "date-time",
                                    "example": "2020-06-12 12:37:32"
                                }
                            },
                            "type": "object"
                        }
                    }
                }
            }
        },
    },
}
